dotenvage\__init__.py
dotenvage\__init__.pyi
dotenvage\dotenvage.pyd
dotenvage\py.typed
dotenvage-0.3.2.dist-info\METADATA
dotenvage-0.3.2.dist-info\WHEEL
dotenvage.pyi
py.typed
dotenvage-0.3.2.dist-info\RECORD
