Metadata-Version: 2.4
Name: dotenvage
Version: 0.3.2
Classifier: Development Status :: 4 - Beta
Classifier: Intended Audience :: Developers
Classifier: Operating System :: OS Independent
Classifier: Programming Language :: Python :: 3
Classifier: Programming Language :: Python :: 3.10
Classifier: Programming Language :: Python :: 3.11
Classifier: Programming Language :: Python :: 3.12
Classifier: Programming Language :: Python :: 3.13
Classifier: Programming Language :: Python :: 3.14
Classifier: Programming Language :: Rust
Classifier: Topic :: Security :: Cryptography
Classifier: Topic :: Software Development :: Libraries :: Python Modules
Summary: Python bindings for dotenvage - encrypt secrets in .env files using age encryption
Keywords: dotenv,age,encryption,secrets,environment
Author-email: Jacobus Geluk <jacobus.geluk@dataroad.com>
License-Expression: CC-BY-SA-4.0
Requires-Python: >=3.10
Project-URL: Documentation, https://docs.rs/dotenvage
Project-URL: Homepage, https://github.com/dataroadinc/dotenvage
Project-URL: Repository, https://github.com/dataroadinc/dotenvage
